[{"gps":null,"_id":"5c6ced2442dd8914f1fdaf1f","profile":"5971ca164e7b8d5ea27f0488","year":2018,"etl":"5acdd6b5166dcc46cbcf4786","srcId":"10332000718","name":"Místní akční plán  vzdělávání","items":[],"paragraphs":[{"_id":"5c6ced2e42dd8914f1fdb7ac","id":"6330","budgetExpenditureAmount":185700,"expenditureAmount":185721.2},{"_id":"5c6ced2e42dd8914f1fdb7ab","id":"6171","budgetExpenditureAmount":9300,"expenditureAmount":-2230.15},{"_id":"5c6ced2e42dd8914f1fdb7aa","id":"3299","budgetExpenditureAmount":100,"expenditureAmount":449910.31}],"budgetExpenditureAmount":195100,"expenditureAmount":633401.36,"budgetIncomeAmount":0,"incomeAmount":0,"__v":0},{"gps":null,"_id":"5c6ced2442dd8914f1fdaf23","profile":"5971ca164e7b8d5ea27f0488","year":2018,"etl":"5acdd6b5166dcc46cbcf4786","srcId":"31107","name":"ZPS","items":[{"_id":"5c6ced2e42dd8914f1fdb7ae","id":"4131","budgetExpenditureAmount":0,"budgetIncomeAmount":26334300,"expenditureAmount":0,"incomeAmount":12489471}],"paragraphs":[{"_id":"5c6ced2e42dd8914f1fdb7b6","id":"6310","budgetExpenditureAmount":150000,"expenditureAmount":118572.17},{"_id":"5c6ced2e42dd8914f1fdb7b5","id":"2219","budgetExpenditureAmount":2081300,"expenditureAmount":2081300},{"_id":"5c6ced2e42dd8914f1fdb7b4","id":"6171","budgetExpenditureAmount":2983000,"expenditureAmount":2804840.090000001},{"_id":"5c6ced2e42dd8914f1fdb7b3","id":"3421","budgetExpenditureAmount":194000,"expenditureAmount":166377.22},{"_id":"5c6ced2e42dd8914f1fdb7b2","id":"3745","budgetExpenditureAmount":1112000,"expenditureAmount":1111802.3},{"_id":"5c6ced2e42dd8914f1fdb7b1","id":"3722","budgetExpenditureAmount":1376000,"expenditureAmount":1337397.1800000002},{"_id":"5c6ced2e42dd8914f1fdb7b0","id":"4339","budgetExpenditureAmount":0,"expenditureAmount":5.4569682106375694e-12},{"_id":"5c6ced2e42dd8914f1fdb7af","id":"6409","budgetExpenditureAmount":13844800,"expenditureAmount":0}],"budgetExpenditureAmount":21741100,"expenditureAmount":7620288.960000002,"budgetIncomeAmount":26334300,"incomeAmount":12489471,"__v":0},{"gps":null,"_id":"5c6ced2442dd8914f1fdaf2f","profile":"5971ca164e7b8d5ea27f0488","year":2018,"etl":"5acdd6b5166dcc46cbcf4786","srcId":"604","name":"ORG.604 - NAKLADY RIZENI","items":[{"_id":"5c6ced2e42dd8914f1fdb7b9","id":"2324","budgetExpenditureAmount":0,"budgetIncomeAmount":0,"expenditureAmount":0,"incomeAmount":126056.26000000001},{"_id":"5c6ced2e42dd8914f1fdb7b8","id":"2111","budgetExpenditureAmount":0,"budgetIncomeAmount":0,"expenditureAmount":0,"incomeAmount":31776.93}],"paragraphs":[],"budgetExpenditureAmount":0,"expenditureAmount":0,"budgetIncomeAmount":0,"incomeAmount":157833.19,"__v":0},{"gps":null,"_id":"5c6ced2442dd8914f1fdaf47","profile":"5971ca164e7b8d5ea27f0488","year":2018,"etl":"5acdd6b5166dcc46cbcf4786","srcId":"819","name":"ZIVOTNI POJISTENI","items":[],"paragraphs":[{"_id":"5c6ced2e42dd8914f1fdb7bb","id":"6171","budgetExpenditureAmount":182800,"expenditureAmount":169760}],"budgetExpenditureAmount":182800,"expenditureAmount":169760,"budgetIncomeAmount":0,"incomeAmount":0,"__v":0},{"gps":null,"_id":"5c6ced2442dd8914f1fdaf48","profile":"5971ca164e7b8d5ea27f0488","year":2018,"etl":"5acdd6b5166dcc46cbcf4786","srcId":"818","name":"Penzijní připojištění","items":[],"paragraphs":[{"_id":"5c6ced2e42dd8914f1fdb7be","id":"6112","budgetExpenditureAmount":18000,"expenditureAmount":12000},{"_id":"5c6ced2e42dd8914f1fdb7bd","id":"6171","budgetExpenditureAmount":673100,"expenditureAmount":487300}],"budgetExpenditureAmount":691100,"expenditureAmount":499300,"budgetIncomeAmount":0,"incomeAmount":0,"__v":0},{"gps":null,"_id":"5c6ced2442dd8914f1fdaf49","profile":"5971ca164e7b8d5ea27f0488","year":2018,"etl":"5acdd6b5166dcc46cbcf4786","srcId":"820","name":"ZIVOTNI JUBILEA","items":[],"paragraphs":[{"_id":"5c6ced2e42dd8914f1fdb7c0","id":"6171","budgetExpenditureAmount":265000,"expenditureAmount":265000}],"budgetExpenditureAmount":265000,"expenditureAmount":265000,"budgetIncomeAmount":0,"incomeAmount":0,"__v":0},{"gps":null,"_id":"5c6ced2442dd8914f1fdaf55","profile":"5971ca164e7b8d5ea27f0488","year":2018,"etl":"5acdd6b5166dcc46cbcf4786","srcId":"2111","name":"HOBULET","items":[{"_id":"5c6ced2e42dd8914f1fdb7c2","id":"2328","budgetExpenditureAmount":0,"budgetIncomeAmount":0,"expenditureAmount":0,"incomeAmount":-71272.98000000001}],"paragraphs":[{"_id":"5c6ced2e42dd8914f1fdb7c3","id":"3349","budgetExpenditureAmount":1585000,"expenditureAmount":1522132.1}],"budgetExpenditureAmount":1585000,"expenditureAmount":1522132.1,"budgetIncomeAmount":0,"incomeAmount":-71272.98000000001,"__v":0},{"gps":null,"_id":"5c6ced2442dd8914f1fdaf70","profile":"5971ca164e7b8d5ea27f0488","year":2018,"etl":"5acdd6b5166dcc46cbcf4786","srcId":"303","name":"MŠ  NAD ŠTOLOU","items":[],"paragraphs":[{"_id":"5c6ced2e42dd8914f1fdb7c5","id":"3111","budgetExpenditureAmount":3159000,"expenditureAmount":3079970}],"budgetExpenditureAmount":3159000,"expenditureAmount":3079970,"budgetIncomeAmount":0,"incomeAmount":0,"__v":0},{"gps":null,"_id":"5c6ced2442dd8914f1fdaf77","profile":"5971ca164e7b8d5ea27f0488","year":2018,"etl":"5acdd6b5166dcc46cbcf4786","srcId":"326","name":"ZŠ TUSAROVA","items":[{"_id":"5c6ced2e42dd8914f1fdb7c7","id":"2328","budgetExpenditureAmount":0,"budgetIncomeAmount":0,"expenditureAmount":0,"incomeAmount":1000}],"paragraphs":[{"_id":"5c6ced2e42dd8914f1fdb7c9","id":"3111","budgetExpenditureAmount":2975600,"expenditureAmount":2858584.45},{"_id":"5c6ced2e42dd8914f1fdb7c8","id":"3113","budgetExpenditureAmount":6449000,"expenditureAmount":6449000}],"budgetExpenditureAmount":9424600,"expenditureAmount":9307584.45,"budgetIncomeAmount":0,"incomeAmount":1000,"__v":0},{"gps":null,"_id":"5c6ced2442dd8914f1fdaf79","profile":"5971ca164e7b8d5ea27f0488","year":2018,"etl":"5acdd6b5166dcc46cbcf4786","srcId":"414016","name":"Obnova zeleně","items":[],"paragraphs":[{"_id":"5c6ced2e42dd8914f1fdb7cb","id":"3745","budgetExpenditureAmount":2670000,"expenditureAmount":2656606.3499999996}],"budgetExpenditureAmount":2670000,"expenditureAmount":2656606.3499999996,"budgetIncomeAmount":0,"incomeAmount":0,"__v":0},{"gps":null,"_id":"5c6ced2442dd8914f1fdaf7b","profile":"5971ca164e7b8d5ea27f0488","year":2018,"etl":"5acdd6b5166dcc46cbcf4786","srcId":"321","name":"Dodavatelé","items":[],"paragraphs":[{"_id":"5c6ced2e42dd8914f1fdb7cd","id":"3113","budgetExpenditureAmount":10055100,"expenditureAmount":10055100}],"budgetExpenditureAmount":10055100,"expenditureAmount":10055100,"budgetIncomeAmount":0,"incomeAmount":0,"__v":0},{"gps":null,"_id":"5c6ced2442dd8914f1fdaf7d","profile":"5971ca164e7b8d5ea27f0488","year":2018,"etl":"5acdd6b5166dcc46cbcf4786","srcId":"327","name":"ZŠ T.G.M. ORTENOVO NÁMĚSTÍ","items":[],"paragraphs":[{"_id":"5c6ced2e42dd8914f1fdb7cf","id":"3113","budgetExpenditureAmount":3906700,"expenditureAmount":3906700}],"budgetExpenditureAmount":3906700,"expenditureAmount":3906700,"budgetIncomeAmount":0,"incomeAmount":0,"__v":0},{"gps":null,"_id":"5c6ced2442dd8914f1fdaf7f","profile":"5971ca164e7b8d5ea27f0488","year":2018,"etl":"5acdd6b5166dcc46cbcf4786","srcId":"325","name":"ZŠ FR. PLAMÍNKOVÉ","items":[],"paragraphs":[{"_id":"5c6ced2e42dd8914f1fdb7d1","id":"3113","budgetExpenditureAmount":5432900,"expenditureAmount":5432900}],"budgetExpenditureAmount":5432900,"expenditureAmount":5432900,"budgetIncomeAmount":0,"incomeAmount":0,"__v":0},{"gps":null,"_id":"5c6ced2442dd8914f1fdaf81","profile":"5971ca164e7b8d5ea27f0488","year":2018,"etl":"5acdd6b5166dcc46cbcf4786","srcId":"322","name":"ZŠ KORUNOVAČNÍ","items":[],"paragraphs":[{"_id":"5c6ced2e42dd8914f1fdb7d3","id":"3113","budgetExpenditureAmount":6625200,"expenditureAmount":6625200}],"budgetExpenditureAmount":6625200,"expenditureAmount":6625200,"budgetIncomeAmount":0,"incomeAmount":0,"__v":0},{"gps":null,"_id":"5c6ced2442dd8914f1fdaf83","profile":"5971ca164e7b8d5ea27f0488","year":2018,"etl":"5acdd6b5166dcc46cbcf4786","srcId":"323","name":"FZŠ UMĚLECKÁ","items":[{"_id":"5c6ced2e42dd8914f1fdb7d5","id":"2229","budgetExpenditureAmount":0,"budgetIncomeAmount":128700,"expenditureAmount":0,"incomeAmount":128646.05}],"paragraphs":[{"_id":"5c6ced2e42dd8914f1fdb7d7","id":"3111","budgetExpenditureAmount":1266300,"expenditureAmount":1266300},{"_id":"5c6ced2e42dd8914f1fdb7d6","id":"3113","budgetExpenditureAmount":7653300,"expenditureAmount":7653246.05}],"budgetExpenditureAmount":8919600,"expenditureAmount":8919546.05,"budgetIncomeAmount":128700,"incomeAmount":128646.05,"__v":0},{"gps":null,"_id":"5c6ced2442dd8914f1fdaf85","profile":"5971ca164e7b8d5ea27f0488","year":2018,"etl":"5acdd6b5166dcc46cbcf4786","srcId":"302","name":"MŠ U URANIE","items":[{"_id":"5c6ced2e42dd8914f1fdb7d9","id":"2229","budgetExpenditureAmount":0,"budgetIncomeAmount":513000,"expenditureAmount":0,"incomeAmount":512947.07}],"paragraphs":[{"_id":"5c6ced2e42dd8914f1fdb7da","id":"3111","budgetExpenditureAmount":4904400,"expenditureAmount":4904347.07}],"budgetExpenditureAmount":4904400,"expenditureAmount":4904347.07,"budgetIncomeAmount":513000,"incomeAmount":512947.07,"__v":0},{"gps":null,"_id":"5c6ced2442dd8914f1fdaf87","profile":"5971ca164e7b8d5ea27f0488","year":2018,"etl":"5acdd6b5166dcc46cbcf4786","srcId":"301","name":"ODBĚRATELÉ","items":[{"_id":"5c6ced2e42dd8914f1fdb7dc","id":"2229","budgetExpenditureAmount":0,"budgetIncomeAmount":790000,"expenditureAmount":0,"incomeAmount":790003.12}],"paragraphs":[{"_id":"5c6ced2e42dd8914f1fdb7dd","id":"3111","budgetExpenditureAmount":2741700,"expenditureAmount":2741703.12}],"budgetExpenditureAmount":2741700,"expenditureAmount":2741703.12,"budgetIncomeAmount":790000,"incomeAmount":790003.12,"__v":0},{"gps":null,"_id":"5c6ced2442dd8914f1fdaf8a","profile":"5971ca164e7b8d5ea27f0488","year":2018,"etl":"5acdd6b5166dcc46cbcf4786","srcId":"304","name":"MŠ LETOHRADSKÁ","items":[{"_id":"5c6ced2e42dd8914f1fdb7df","id":"2229","budgetExpenditureAmount":0,"budgetIncomeAmount":256000,"expenditureAmount":0,"incomeAmount":255984.94}],"paragraphs":[{"_id":"5c6ced2e42dd8914f1fdb7e0","id":"3111","budgetExpenditureAmount":3133400,"expenditureAmount":3133384.94}],"budgetExpenditureAmount":3133400,"expenditureAmount":3133384.94,"budgetIncomeAmount":256000,"incomeAmount":255984.94,"__v":0},{"gps":null,"_id":"5c6ced2442dd8914f1fdaf8e","profile":"5971ca164e7b8d5ea27f0488","year":2018,"etl":"5acdd6b5166dcc46cbcf4786","srcId":"316","name":"MŠ NA VÝŠINÁCH","items":[{"_id":"5c6ced2e42dd8914f1fdb7e2","id":"2229","budgetExpenditureAmount":0,"budgetIncomeAmount":539500,"expenditureAmount":0,"incomeAmount":547037.44}],"paragraphs":[{"_id":"5c6ced2e42dd8914f1fdb7e3","id":"3111","budgetExpenditureAmount":3518900,"expenditureAmount":3518837.44}],"budgetExpenditureAmount":3518900,"expenditureAmount":3518837.44,"budgetIncomeAmount":539500,"incomeAmount":547037.44,"__v":0},{"gps":null,"_id":"5c6ced2442dd8914f1fdaf95","profile":"5971ca164e7b8d5ea27f0488","year":2018,"etl":"5acdd6b5166dcc46cbcf4786","srcId":"80180441016","name":"Reko střechy ZŠ TGM","items":[],"paragraphs":[{"_id":"5c6ced2e42dd8914f1fdb7e5","id":"3113","budgetExpenditureAmount":2410100,"expenditureAmount":2278345.98}],"budgetExpenditureAmount":2410100,"expenditureAmount":2278345.98,"budgetIncomeAmount":0,"incomeAmount":0,"__v":0},{"gps":null,"_id":"5c6ced2442dd8914f1fdaf97","profile":"5971ca164e7b8d5ea27f0488","year":2018,"etl":"5acdd6b5166dcc46cbcf4786","srcId":"80371426016","name":"ZŠ Fr. Křížka - reko kuchyně","items":[],"paragraphs":[{"_id":"5c6ced2e42dd8914f1fdb7e7","id":"3113","budgetExpenditureAmount":1615300,"expenditureAmount":492237}],"budgetExpenditureAmount":1615300,"expenditureAmount":492237,"budgetIncomeAmount":0,"incomeAmount":0,"__v":0},{"gps":null,"_id":"5c6ced2442dd8914f1fdaf99","profile":"5971ca164e7b8d5ea27f0488","year":2018,"etl":"5acdd6b5166dcc46cbcf4786","srcId":"471017","name":"MŠ Ortenovo nám. - zateplení PD, reko zahrady","items":[],"paragraphs":[{"_id":"5c6ced2e42dd8914f1fdb7e9","id":"3111","budgetExpenditureAmount":2483000,"expenditureAmount":2286643}],"budgetExpenditureAmount":2483000,"expenditureAmount":2286643,"budgetIncomeAmount":0,"incomeAmount":0,"__v":0},{"gps":null,"_id":"5c6ced2442dd8914f1fdaf9e","profile":"5971ca164e7b8d5ea27f0488","year":2018,"etl":"5acdd6b5166dcc46cbcf4786","srcId":"2350267500017","name":"OPP -pĺ růstu MŠ Na Výšinách, navýš.kapacity","items":[],"paragraphs":[{"_id":"5c6ced2e42dd8914f1fdb7ec","id":"3111","budgetExpenditureAmount":7721200,"expenditureAmount":7243447.010000002},{"_id":"5c6ced2e42dd8914f1fdb7eb","id":"6330","budgetExpenditureAmount":326500,"expenditureAmount":326491.87}],"budgetExpenditureAmount":8047700,"expenditureAmount":7569938.880000002,"budgetIncomeAmount":0,"incomeAmount":0,"__v":0},{"gps":null,"_id":"5c6ced2442dd8914f1fdafa0","profile":"5971ca164e7b8d5ea27f0488","year":2018,"etl":"5acdd6b5166dcc46cbcf4786","srcId":"80037254010","name":"Reko vodárenská  věž","items":[],"paragraphs":[{"_id":"5c6ced2e42dd8914f1fdb7ef","id":"3322","budgetExpenditureAmount":24556600,"expenditureAmount":22650149.959999997},{"_id":"5c6ced2e42dd8914f1fdb7ee","id":"3111","budgetExpenditureAmount":0,"expenditureAmount":0}],"budgetExpenditureAmount":24556600,"expenditureAmount":22650149.96,"budgetIncomeAmount":0,"incomeAmount":0,"__v":0},{"gps":null,"_id":"5c6ced2442dd8914f1fdafa4","profile":"5971ca164e7b8d5ea27f0488","year":2018,"etl":"5acdd6b5166dcc46cbcf4786","srcId":"80495432016","name":"Poliklinika","items":[],"paragraphs":[{"_id":"5c6ced2e42dd8914f1fdb7f2","id":"3519","budgetExpenditureAmount":14060200,"expenditureAmount":12198249},{"_id":"5c6ced2e42dd8914f1fdb7f1","id":"3515","budgetExpenditureAmount":14698000,"expenditureAmount":14698000}],"budgetExpenditureAmount":28758200,"expenditureAmount":26896248.999999996,"budgetIncomeAmount":0,"incomeAmount":0,"__v":0},{"gps":null,"_id":"5c6ced2442dd8914f1fdafae","profile":"5971ca164e7b8d5ea27f0488","year":2018,"etl":"5acdd6b5166dcc46cbcf4786","srcId":"9816","name":"dotace VHP v r. 2016","items":[{"_id":"5c6ced2e42dd8914f1fdb7f4","id":"2229","budgetExpenditureAmount":0,"budgetIncomeAmount":5800,"expenditureAmount":0,"incomeAmount":5729}],"paragraphs":[{"_id":"5c6ced2e42dd8914f1fdb7f5","id":"3419","budgetExpenditureAmount":977800,"expenditureAmount":741356}],"budgetExpenditureAmount":977800,"expenditureAmount":741356,"budgetIncomeAmount":5800,"incomeAmount":5729,"__v":0},{"gps":null,"_id":"5c6ced2442dd8914f1fdafbb","profile":"5971ca164e7b8d5ea27f0488","year":2018,"etl":"5acdd6b5166dcc46cbcf4786","srcId":"457016","name":"Repas výlohy městské knihovny","items":[],"paragraphs":[{"_id":"5c6ced2e42dd8914f1fdb7f7","id":"3613","budgetExpenditureAmount":1228600,"expenditureAmount":1022723.8500000001}],"budgetExpenditureAmount":1228600,"expenditureAmount":1022723.8500000001,"budgetIncomeAmount":0,"incomeAmount":0,"__v":0},{"gps":null,"_id":"5c6ced2442dd8914f1fdafbe","profile":"5971ca164e7b8d5ea27f0488","year":2018,"etl":"5acdd6b5166dcc46cbcf4786","srcId":"480017","name":"NBP U Průhonu 11/1493","items":[],"paragraphs":[{"_id":"5c6ced2e42dd8914f1fdb7f9","id":"3613","budgetExpenditureAmount":12937000,"expenditureAmount":11109076.82}],"budgetExpenditureAmount":12937000,"expenditureAmount":11109076.82,"budgetIncomeAmount":0,"incomeAmount":0,"__v":0},{"gps":null,"_id":"5c6ced2442dd8914f1fdafc0","profile":"5971ca164e7b8d5ea27f0488","year":2018,"etl":"5acdd6b5166dcc46cbcf4786","srcId":"373015","name":"ZŠ Strossmayer.n., bud.Letohradská-soubor nábytku","items":[],"paragraphs":[{"_id":"5c6ced2e42dd8914f1fdb7fb","id":"3612","budgetExpenditureAmount":0,"expenditureAmount":0}],"budgetExpenditureAmount":0,"expenditureAmount":0,"budgetIncomeAmount":0,"incomeAmount":0,"__v":0},{"gps":null,"_id":"5c6ced2442dd8914f1fdafcf","profile":"5971ca164e7b8d5ea27f0488","year":2018,"etl":"5acdd6b5166dcc46cbcf4786","srcId":"409015","name":"Nová radnice","items":[],"paragraphs":[{"_id":"5c6ced2e42dd8914f1fdb7fd","id":"6171","budgetExpenditureAmount":277090500,"expenditureAmount":44264050.910000004}],"budgetExpenditureAmount":277090500,"expenditureAmount":44264050.910000004,"budgetIncomeAmount":0,"incomeAmount":0,"__v":0},{"gps":null,"_id":"5c6ced2442dd8914f1fdafd3","profile":"5971ca164e7b8d5ea27f0488","year":2018,"etl":"5acdd6b5166dcc46cbcf4786","srcId":"10","name":"Humanitní fond","items":[{"_id":"5c6ced2e42dd8914f1fdb800","id":"2460","budgetExpenditureAmount":0,"budgetIncomeAmount":0,"expenditureAmount":0,"incomeAmount":21300},{"_id":"5c6ced2e42dd8914f1fdb7ff","id":"2321","budgetExpenditureAmount":0,"budgetIncomeAmount":144000,"expenditureAmount":0,"incomeAmount":144000}],"paragraphs":[{"_id":"5c6ced2e42dd8914f1fdb802","id":"4399","budgetExpenditureAmount":394000,"expenditureAmount":370804},{"_id":"5c6ced2e42dd8914f1fdb801","id":"6409","budgetExpenditureAmount":231400,"expenditureAmount":0}],"budgetExpenditureAmount":625400,"expenditureAmount":370804,"budgetIncomeAmount":144000,"incomeAmount":165300,"__v":0},{"gps":null,"_id":"5c6ced2442dd8914f1fdafd8","profile":"5971ca164e7b8d5ea27f0488","year":2018,"etl":"5acdd6b5166dcc46cbcf4786","srcId":"516615","name":"Právní služby FK Legal","items":[],"paragraphs":[{"_id":"5c6ced2e42dd8914f1fdb804","id":"6171","budgetExpenditureAmount":250000,"expenditureAmount":1149.5}],"budgetExpenditureAmount":250000,"expenditureAmount":1149.5,"budgetIncomeAmount":0,"incomeAmount":0,"__v":0},{"gps":null,"_id":"5c6ced2442dd8914f1fdafdd","profile":"5971ca164e7b8d5ea27f0488","year":2018,"etl":"5acdd6b5166dcc46cbcf4786","srcId":"2370352000304","name":"OPP-pól růstu MŠ Letohradská z Pohádky do pohádky","items":[{"_id":"5c6ced2e42dd8914f1fdb806","id":"4137","budgetExpenditureAmount":0,"budgetIncomeAmount":199800,"expenditureAmount":0,"incomeAmount":197590.59}],"paragraphs":[{"_id":"5c6ced2e42dd8914f1fdb807","id":"3111","budgetExpenditureAmount":1958600,"expenditureAmount":1627590.59}],"budgetExpenditureAmount":1958600,"expenditureAmount":1627590.59,"budgetIncomeAmount":199800,"incomeAmount":197590.59,"__v":0},{"gps":null,"_id":"5c6ced2442dd8914f1fdafde","profile":"5971ca164e7b8d5ea27f0488","year":2018,"etl":"5acdd6b5166dcc46cbcf4786","srcId":"817","name":"FLEXIPASY","items":[],"paragraphs":[{"_id":"5c6ced2e42dd8914f1fdb809","id":"6171","budgetExpenditureAmount":2701000,"expenditureAmount":2668194.38}],"budgetExpenditureAmount":2701000,"expenditureAmount":2668194.38,"budgetIncomeAmount":0,"incomeAmount":0,"__v":0},{"gps":null,"_id":"5c6ced2442dd8914f1fdafe3","profile":"5971ca164e7b8d5ea27f0488","year":2018,"etl":"5acdd6b5166dcc46cbcf4786","srcId":"814","name":"SFP - CVICENI","items":[],"paragraphs":[{"_id":"5c6ced2e42dd8914f1fdb80b","id":"6171","budgetExpenditureAmount":8200,"expenditureAmount":5100}],"budgetExpenditureAmount":8200,"expenditureAmount":5100,"budgetIncomeAmount":0,"incomeAmount":0,"__v":0},{"gps":null,"_id":"5c6ced2442dd8914f1fdaff2","profile":"5971ca164e7b8d5ea27f0488","year":2018,"etl":"5acdd6b5166dcc46cbcf4786","srcId":"782","name":"STRAVENKY - ORGANIZACE","items":[],"paragraphs":[{"_id":"5c6ced2e42dd8914f1fdb80d","id":"6171","budgetExpenditureAmount":2651400,"expenditureAmount":2651390.5}],"budgetExpenditureAmount":2651400,"expenditureAmount":2651390.5,"budgetIncomeAmount":0,"incomeAmount":0,"__v":0},{"gps":null,"_id":"5c6ced2442dd8914f1fdaff3","profile":"5971ca164e7b8d5ea27f0488","year":2018,"etl":"5acdd6b5166dcc46cbcf4786","srcId":"815","name":"SFP","items":[],"paragraphs":[{"_id":"5c6ced2e42dd8914f1fdb80f","id":"6171","budgetExpenditureAmount":1400800,"expenditureAmount":1222379.5}],"budgetExpenditureAmount":1400800,"expenditureAmount":1222379.5,"budgetIncomeAmount":0,"incomeAmount":0,"__v":0},{"gps":null,"_id":"5c6ced2442dd8914f1fdaff8","profile":"5971ca164e7b8d5ea27f0488","year":2018,"etl":"5acdd6b5166dcc46cbcf4786","srcId":"472017","name":"Půdní prostor ZŠ Letohradská","items":[],"paragraphs":[{"_id":"5c6ced2e42dd8914f1fdb811","id":"3113","budgetExpenditureAmount":0,"expenditureAmount":0}],"budgetExpenditureAmount":0,"expenditureAmount":0,"budgetIncomeAmount":0,"incomeAmount":0,"__v":0},{"gps":null,"_id":"5c6ced2442dd8914f1fdb004","profile":"5971ca164e7b8d5ea27f0488","year":2018,"etl":"5acdd6b5166dcc46cbcf4786","srcId":"383015","name":"U Průhonu 52 - inv.akce","items":[],"paragraphs":[{"_id":"5c6ced2e42dd8914f1fdb813","id":"3612","budgetExpenditureAmount":4796700,"expenditureAmount":3697491.480000002}],"budgetExpenditureAmount":4796700,"expenditureAmount":3697491.480000002,"budgetIncomeAmount":0,"incomeAmount":0,"__v":0},{"gps":null,"_id":"5c6ced2442dd8914f1fdb00a","profile":"5971ca164e7b8d5ea27f0488","year":2018,"etl":"5acdd6b5166dcc46cbcf4786","srcId":"483017","name":"DH Sedmikráska","items":[],"paragraphs":[{"_id":"5c6ced2e42dd8914f1fdb815","id":"3421","budgetExpenditureAmount":1621000,"expenditureAmount":-1979089.25}],"budgetExpenditureAmount":1621000,"expenditureAmount":-1979089.25,"budgetIncomeAmount":0,"incomeAmount":0,"__v":0},{"gps":null,"_id":"5c6ced2442dd8914f1fdb00d","profile":"5971ca164e7b8d5ea27f0488","year":2018,"etl":"5acdd6b5166dcc46cbcf4786","srcId":"479017","name":"Archiv MČ","items":[],"paragraphs":[{"_id":"5c6ced2e42dd8914f1fdb817","id":"3613","budgetExpenditureAmount":4500000,"expenditureAmount":3413234.3000000007}],"budgetExpenditureAmount":4500000,"expenditureAmount":3413234.3000000007,"budgetIncomeAmount":0,"incomeAmount":0,"__v":0},{"gps":null,"_id":"5c6ced2442dd8914f1fdb021","profile":"5971ca164e7b8d5ea27f0488","year":2018,"etl":"5acdd6b5166dcc46cbcf4786","srcId":"442016","name":"Oprava objektu  u Uranie 14-rozšíření kapacity  ZŠ","items":[],"paragraphs":[{"_id":"5c6ced2e42dd8914f1fdb819","id":"3113","budgetExpenditureAmount":104100,"expenditureAmount":46250}],"budgetExpenditureAmount":104100,"expenditureAmount":46250,"budgetIncomeAmount":0,"incomeAmount":0,"__v":0},{"gps":null,"_id":"5c6ced2442dd8914f1fdb025","profile":"5971ca164e7b8d5ea27f0488","year":2018,"etl":"5acdd6b5166dcc46cbcf4786","srcId":"812","name":"SFZ - REKREACE - DETI","items":[],"paragraphs":[{"_id":"5c6ced2e42dd8914f1fdb81b","id":"6171","budgetExpenditureAmount":25000,"expenditureAmount":22000}],"budgetExpenditureAmount":25000,"expenditureAmount":22000,"budgetIncomeAmount":0,"incomeAmount":0,"__v":0},{"gps":null,"_id":"5c6ced2442dd8914f1fdb02e","profile":"5971ca164e7b8d5ea27f0488","year":2018,"etl":"5acdd6b5166dcc46cbcf4786","srcId":"10631007235","name":"MA21 - implementace soc. bydlení","items":[{"_id":"5c6ced2e42dd8914f1fdb81d","id":"4137","budgetExpenditureAmount":0,"budgetIncomeAmount":422900,"expenditureAmount":0,"incomeAmount":422850.8600000001}],"paragraphs":[{"_id":"5c6ced2e42dd8914f1fdb81e","id":"4399","budgetExpenditureAmount":4777200,"expenditureAmount":2600171.4800000004}],"budgetExpenditureAmount":4777200,"expenditureAmount":2600171.4800000004,"budgetIncomeAmount":422900,"incomeAmount":422850.8600000001,"__v":0},{"gps":null,"_id":"5c6ced2442dd8914f1fdb030","profile":"5971ca164e7b8d5ea27f0488","year":2018,"etl":"5acdd6b5166dcc46cbcf4786","srcId":"2018","name":"Nadační fond","items":[{"_id":"5c6ced2e42dd8914f1fdb820","id":"2321","budgetExpenditureAmount":0,"budgetIncomeAmount":0,"expenditureAmount":0,"incomeAmount":0}],"paragraphs":[{"_id":"5c6ced2e42dd8914f1fdb821","id":"4399","budgetExpenditureAmount":0,"expenditureAmount":0}],"budgetExpenditureAmount":0,"expenditureAmount":0,"budgetIncomeAmount":0,"incomeAmount":0,"__v":0},{"gps":null,"_id":"5c6ced2442dd8914f1fdb03d","profile":"5971ca164e7b8d5ea27f0488","year":2018,"etl":"5acdd6b5166dcc46cbcf4786","srcId":"911","name":"DPH","items":[],"paragraphs":[{"_id":"5c6ced2e42dd8914f1fdb823","id":"6171","budgetExpenditureAmount":0,"expenditureAmount":0}],"budgetExpenditureAmount":0,"expenditureAmount":0,"budgetIncomeAmount":0,"incomeAmount":0,"__v":0},{"gps":null,"_id":"5c6ced2442dd8914f1fdb044","profile":"5971ca164e7b8d5ea27f0488","year":2018,"etl":"5acdd6b5166dcc46cbcf4786","srcId":"2321","name":"JATECNI- DETSKE HRISTE","items":[{"_id":"5c6ced2e42dd8914f1fdb825","id":"2321","budgetExpenditureAmount":0,"budgetIncomeAmount":0,"expenditureAmount":0,"incomeAmount":0}],"paragraphs":[],"budgetExpenditureAmount":0,"expenditureAmount":0,"budgetIncomeAmount":0,"incomeAmount":0,"__v":0},{"gps":null,"_id":"5c6ced2442dd8914f1fdb04b","profile":"5971ca164e7b8d5ea27f0488","year":2018,"etl":"5acdd6b5166dcc46cbcf4786","srcId":"456016","name":"NBP U Průhonu 48/1240","items":[],"paragraphs":[{"_id":"5c6ced2e42dd8914f1fdb827","id":"3613","budgetExpenditureAmount":4085000,"expenditureAmount":3379199.69}],"budgetExpenditureAmount":4085000,"expenditureAmount":3379199.69,"budgetIncomeAmount":0,"incomeAmount":0,"__v":0},{"gps":null,"_id":"5c6ced2542dd8914f1fdb059","profile":"5971ca164e7b8d5ea27f0488","year":2018,"etl":"5acdd6b5166dcc46cbcf4786","srcId":"201717","name":"Výkon veřejného opatrovníka u OPČ","items":[],"paragraphs":[{"_id":"5c6ced2e42dd8914f1fdb829","id":"4399","budgetExpenditureAmount":420600,"expenditureAmount":420625}],"budgetExpenditureAmount":420600,"expenditureAmount":420625,"budgetIncomeAmount":0,"incomeAmount":0,"__v":0},{"gps":null,"_id":"5c6ced2542dd8914f1fdb05d","profile":"5971ca164e7b8d5ea27f0488","year":2018,"etl":"5acdd6b5166dcc46cbcf4786","srcId":"2430565502017","name":"OPP-pól růstu Podpora soc.bydlení v P/7","items":[{"_id":"5c6ced2e42dd8914f1fdb82b","id":"4137","budgetExpenditureAmount":0,"budgetIncomeAmount":2964700,"expenditureAmount":0,"incomeAmount":2832763.6}],"paragraphs":[{"_id":"5c6ced2e42dd8914f1fdb82c","id":"3612","budgetExpenditureAmount":6525900,"expenditureAmount":178928.80000000005}],"budgetExpenditureAmount":6525900,"expenditureAmount":178928.80000000005,"budgetIncomeAmount":2964700,"incomeAmount":2832763.6,"__v":0},{"gps":null,"_id":"5c6ced2542dd8914f1fdb06d","profile":"5971ca164e7b8d5ea27f0488","year":2018,"etl":"5acdd6b5166dcc46cbcf4786","srcId":"201818","name":"Výkon veřejného opatrovníka","items":[],"paragraphs":[{"_id":"5c6ced2e42dd8914f1fdb82e","id":"4399","budgetExpenditureAmount":957000,"expenditureAmount":766119}],"budgetExpenditureAmount":957000,"expenditureAmount":766119,"budgetIncomeAmount":0,"incomeAmount":0,"__v":0},{"gps":null,"_id":"5c6ced2542dd8914f1fdb06e","profile":"5971ca164e7b8d5ea27f0488","year":2018,"etl":"5acdd6b5166dcc46cbcf4786","srcId":"9815","name":"VHP za r. 2015","items":[],"paragraphs":[{"_id":"5c6ced2e42dd8914f1fdb830","id":"3419","budgetExpenditureAmount":18600,"expenditureAmount":18600}],"budgetExpenditureAmount":18600,"expenditureAmount":18600,"budgetIncomeAmount":0,"incomeAmount":0,"__v":0},{"gps":null,"_id":"5c6ced2542dd8914f1fdb072","profile":"5971ca164e7b8d5ea27f0488","year":2018,"etl":"5acdd6b5166dcc46cbcf4786","srcId":"14007","name":"spoluúčast 10% 14007","items":[],"paragraphs":[{"_id":"5c6ced2e42dd8914f1fdb832","id":"4342","budgetExpenditureAmount":100000,"expenditureAmount":76417}],"budgetExpenditureAmount":100000,"expenditureAmount":76417,"budgetIncomeAmount":0,"incomeAmount":0,"__v":0},{"gps":null,"_id":"5c6ced2542dd8914f1fdb074","profile":"5971ca164e7b8d5ea27f0488","year":2018,"etl":"5acdd6b5166dcc46cbcf4786","srcId":"777501","name":"PROGRESSIVE","items":[],"paragraphs":[{"_id":"5c6ced2e42dd8914f1fdb834","id":"3541","budgetExpenditureAmount":30000,"expenditureAmount":30000}],"budgetExpenditureAmount":30000,"expenditureAmount":30000,"budgetIncomeAmount":0,"incomeAmount":0,"__v":0},{"gps":null,"_id":"5c6ced2542dd8914f1fdb086","profile":"5971ca164e7b8d5ea27f0488","year":2018,"etl":"5acdd6b5166dcc46cbcf4786","srcId":"777601","name":"MAILKIT","items":[],"paragraphs":[{"_id":"5c6ced2e42dd8914f1fdb836","id":"3349","budgetExpenditureAmount":55700,"expenditureAmount":52102}],"budgetExpenditureAmount":55700,"expenditureAmount":52102,"budgetIncomeAmount":0,"incomeAmount":0,"__v":0},{"gps":null,"_id":"5c6ced2542dd8914f1fdb08b","profile":"5971ca164e7b8d5ea27f0488","year":2018,"etl":"5acdd6b5166dcc46cbcf4786","srcId":"9021","name":"PŘEVOD NA MZDY Z VHČ","items":[],"paragraphs":[{"_id":"5c6ced2e42dd8914f1fdb838","id":"6171","budgetExpenditureAmount":0,"expenditureAmount":-11414742}],"budgetExpenditureAmount":0,"expenditureAmount":-11414742,"budgetIncomeAmount":0,"incomeAmount":0,"__v":0},{"gps":null,"_id":"5c6ced2542dd8914f1fdb090","profile":"5971ca164e7b8d5ea27f0488","year":2018,"etl":"5acdd6b5166dcc46cbcf4786","srcId":"120005","name":"ul. FR. Křížka","items":[],"paragraphs":[{"_id":"5c6ced2e42dd8914f1fdb83a","id":"3699","budgetExpenditureAmount":0,"expenditureAmount":0}],"budgetExpenditureAmount":0,"expenditureAmount":0,"budgetIncomeAmount":0,"incomeAmount":0,"__v":0},{"gps":null,"_id":"5c6ced2542dd8914f1fdb095","profile":"5971ca164e7b8d5ea27f0488","year":2018,"etl":"5acdd6b5166dcc46cbcf4786","srcId":"102018","name":"Programové dotace MČ Praha 7","items":[{"_id":"5c6ced2e42dd8914f1fdb83c","id":"2229","budgetExpenditureAmount":0,"budgetIncomeAmount":0,"expenditureAmount":0,"incomeAmount":0}],"paragraphs":[{"_id":"5c6ced2e42dd8914f1fdb843","id":"3541","budgetExpenditureAmount":200100,"expenditureAmount":200000},{"_id":"5c6ced2e42dd8914f1fdb842","id":"3419","budgetExpenditureAmount":940000,"expenditureAmount":936000},{"_id":"5c6ced2e42dd8914f1fdb841","id":"3792","budgetExpenditureAmount":269000,"expenditureAmount":269000},{"_id":"5c6ced2e42dd8914f1fdb840","id":"3319","budgetExpenditureAmount":2087000,"expenditureAmount":2058000},{"_id":"5c6ced2e42dd8914f1fdb83f","id":"4359","budgetExpenditureAmount":830000,"expenditureAmount":830000},{"_id":"5c6ced2e42dd8914f1fdb83e","id":"3113","budgetExpenditureAmount":142000,"expenditureAmount":103000},{"_id":"5c6ced2e42dd8914f1fdb83d","id":"3111","budgetExpenditureAmount":108000,"expenditureAmount":108000}],"budgetExpenditureAmount":4576100,"expenditureAmount":4504000,"budgetIncomeAmount":0,"incomeAmount":0,"__v":0},{"gps":null,"_id":"5c6ced2542dd8914f1fdb0b8","profile":"5971ca164e7b8d5ea27f0488","year":2018,"etl":"5acdd6b5166dcc46cbcf4786","srcId":"232117","name":"rok 2017","items":[],"paragraphs":[{"_id":"5c6ced2e42dd8914f1fdb845","id":"3113","budgetExpenditureAmount":23700,"expenditureAmount":23019}],"budgetExpenditureAmount":23700,"expenditureAmount":23019,"budgetIncomeAmount":0,"incomeAmount":0,"__v":0},{"gps":null,"_id":"5c6ced2542dd8914f1fdb0bb","profile":"5971ca164e7b8d5ea27f0488","year":2018,"etl":"5acdd6b5166dcc46cbcf4786","srcId":"88","name":"Azylant 2","items":[{"_id":"5c6ced2e42dd8914f1fdb847","id":"2111","budgetExpenditureAmount":0,"budgetIncomeAmount":0,"expenditureAmount":0,"incomeAmount":988}],"paragraphs":[],"budgetExpenditureAmount":0,"expenditureAmount":0,"budgetIncomeAmount":0,"incomeAmount":988,"__v":0},{"gps":null,"_id":"5c6ced2542dd8914f1fdb0c2","profile":"5971ca164e7b8d5ea27f0488","year":2018,"etl":"5acdd6b5166dcc46cbcf4786","srcId":"492017","name":"ZŠ Fr. Křížka","items":[],"paragraphs":[{"_id":"5c6ced2e42dd8914f1fdb849","id":"3113","budgetExpenditureAmount":36600,"expenditureAmount":16940}],"budgetExpenditureAmount":36600,"expenditureAmount":16940,"budgetIncomeAmount":0,"incomeAmount":0,"__v":0},{"gps":null,"_id":"5c6ced2542dd8914f1fdb0e6","profile":"5971ca164e7b8d5ea27f0488","year":2018,"etl":"5acdd6b5166dcc46cbcf4786","srcId":"22005","name":"Jednotné kontaktní místo - spoluúčast MČ","items":[],"paragraphs":[{"_id":"5c6ced2e42dd8914f1fdb84b","id":"6171","budgetExpenditureAmount":300000,"expenditureAmount":251394}],"budgetExpenditureAmount":300000,"expenditureAmount":251394,"budgetIncomeAmount":0,"incomeAmount":0,"__v":0},{"gps":null,"_id":"5c6ced2542dd8914f1fdb0f4","profile":"5971ca164e7b8d5ea27f0488","year":2018,"etl":"5acdd6b5166dcc46cbcf4786","srcId":"181321","name":"ZŠ Letohradská - dotace na rozvoj","items":[],"paragraphs":[{"_id":"5c6ced2e42dd8914f1fdb84d","id":"3113","budgetExpenditureAmount":300000,"expenditureAmount":300000}],"budgetExpenditureAmount":300000,"expenditureAmount":300000,"budgetIncomeAmount":0,"incomeAmount":0,"__v":0},{"gps":null,"_id":"5c6ced2542dd8914f1fdb0f5","profile":"5971ca164e7b8d5ea27f0488","year":2018,"etl":"5acdd6b5166dcc46cbcf4786","srcId":"181322","name":"ZŠ Korunovační - dotace na rozvoj","items":[],"paragraphs":[{"_id":"5c6ced2e42dd8914f1fdb84f","id":"3113","budgetExpenditureAmount":300000,"expenditureAmount":300000}],"budgetExpenditureAmount":300000,"expenditureAmount":300000,"budgetIncomeAmount":0,"incomeAmount":0,"__v":0},{"gps":null,"_id":"5c6ced2542dd8914f1fdb0f6","profile":"5971ca164e7b8d5ea27f0488","year":2018,"etl":"5acdd6b5166dcc46cbcf4786","srcId":"181325","name":"ZŠ Fr. Plamínkové - dotace na rozvoj","items":[],"paragraphs":[{"_id":"5c6ced2e42dd8914f1fdb851","id":"3113","budgetExpenditureAmount":1400000,"expenditureAmount":1400000}],"budgetExpenditureAmount":1400000,"expenditureAmount":1400000,"budgetIncomeAmount":0,"incomeAmount":0,"__v":0},{"gps":null,"_id":"5c6ced2542dd8914f1fdb0fb","profile":"5971ca164e7b8d5ea27f0488","year":2018,"etl":"5acdd6b5166dcc46cbcf4786","srcId":"464017","name":"Pořízení DH U Pergamenky","items":[],"paragraphs":[{"_id":"5c6ced2e42dd8914f1fdb853","id":"3421","budgetExpenditureAmount":3065500,"expenditureAmount":137819}],"budgetExpenditureAmount":3065500,"expenditureAmount":137819,"budgetIncomeAmount":0,"incomeAmount":0,"__v":0},{"gps":null,"_id":"5c6ced2542dd8914f1fdb10e","profile":"5971ca164e7b8d5ea27f0488","year":2018,"etl":"5acdd6b5166dcc46cbcf4786","srcId":"509018","name":"Reko vnitrobloku U vody","items":[],"paragraphs":[{"_id":"5c6ced2e42dd8914f1fdb855","id":"3745","budgetExpenditureAmount":220000,"expenditureAmount":217800}],"budgetExpenditureAmount":220000,"expenditureAmount":217800,"budgetIncomeAmount":0,"incomeAmount":0,"__v":0},{"gps":null,"_id":"5c6ced2542dd8914f1fdb11d","profile":"5971ca164e7b8d5ea27f0488","year":2018,"etl":"5acdd6b5166dcc46cbcf4786","srcId":"387015","name":"Údržba stromů v ZŠ a MŠ","items":[],"paragraphs":[{"_id":"5c6ced2e42dd8914f1fdb857","id":"3113","budgetExpenditureAmount":152700,"expenditureAmount":105835}],"budgetExpenditureAmount":152700,"expenditureAmount":105835,"budgetIncomeAmount":0,"incomeAmount":0,"__v":0},{"gps":null,"_id":"5c6ced2542dd8914f1fdb147","profile":"5971ca164e7b8d5ea27f0488","year":2018,"etl":"5acdd6b5166dcc46cbcf4786","srcId":"10578000323","name":"EU-Šablony FZŠ a MŠ U Studánky, Umělecká","items":[{"_id":"5c6ced2e42dd8914f1fdb859","id":"4137","budgetExpenditureAmount":0,"budgetIncomeAmount":656700,"expenditureAmount":0,"incomeAmount":656700.8}],"paragraphs":[{"_id":"5c6ced2e42dd8914f1fdb85a","id":"3113","budgetExpenditureAmount":656700,"expenditureAmount":656700.8}],"budgetExpenditureAmount":656700,"expenditureAmount":656700.8,"budgetIncomeAmount":656700,"incomeAmount":656700.8,"__v":0},{"gps":null,"_id":"5c6ced2642dd8914f1fdb14d","profile":"5971ca164e7b8d5ea27f0488","year":2018,"etl":"5acdd6b5166dcc46cbcf4786","srcId":"516625","name":"Právní služby VHK Partners","items":[],"paragraphs":[{"_id":"5c6ced2e42dd8914f1fdb85c","id":"6171","budgetExpenditureAmount":250000,"expenditureAmount":66671}],"budgetExpenditureAmount":250000,"expenditureAmount":66671,"budgetIncomeAmount":0,"incomeAmount":0,"__v":0},{"gps":null,"_id":"5c6ced2642dd8914f1fdb189","profile":"5971ca164e7b8d5ea27f0488","year":2018,"etl":"5acdd6b5166dcc46cbcf4786","srcId":"9817","name":"Odvod z  VHP v r. 2017","items":[],"paragraphs":[{"_id":"5c6ced2e42dd8914f1fdb85f","id":"3419","budgetExpenditureAmount":4680500,"expenditureAmount":2095257},{"_id":"5c6ced2e42dd8914f1fdb85e","id":"3119","budgetExpenditureAmount":17100,"expenditureAmount":0}],"budgetExpenditureAmount":4697600,"expenditureAmount":2095257,"budgetIncomeAmount":0,"incomeAmount":0,"__v":0},{"gps":null,"_id":"5c6ced2642dd8914f1fdb18b","profile":"5971ca164e7b8d5ea27f0488","year":2018,"etl":"5acdd6b5166dcc46cbcf4786","srcId":"80686484017","name":"Reko školního sport. areálu při ZŠ TGM","items":[{"_id":"5c6ced2e42dd8914f1fdb861","id":"4137","budgetExpenditureAmount":0,"budgetIncomeAmount":1000000,"expenditureAmount":0,"incomeAmount":1000000}],"paragraphs":[{"_id":"5c6ced2e42dd8914f1fdb862","id":"3113","budgetExpenditureAmount":16902500,"expenditureAmount":5995860.08}],"budgetExpenditureAmount":16902500,"expenditureAmount":5995860.08,"budgetIncomeAmount":1000000,"incomeAmount":1000000,"__v":0},{"gps":null,"_id":"5c6ced2642dd8914f1fdb1d2","profile":"5971ca164e7b8d5ea27f0488","year":2018,"etl":"5acdd6b5166dcc46cbcf4786","srcId":"497017","name":"Dukelských Hrdinů 1","items":[],"paragraphs":[{"_id":"5c6ced2e42dd8914f1fdb864","id":"3519","budgetExpenditureAmount":0,"expenditureAmount":0}],"budgetExpenditureAmount":0,"expenditureAmount":0,"budgetIncomeAmount":0,"incomeAmount":0,"__v":0},{"gps":null,"_id":"5c6ced2642dd8914f1fdb1d7","profile":"5971ca164e7b8d5ea27f0488","year":2018,"etl":"5acdd6b5166dcc46cbcf4786","srcId":"10446000000","name":"Šablony pro MŠ a ZŠ I. - projekt zjednodušeného vy","items":[{"_id":"5c6ced2e42dd8914f1fdb866","id":"4137","budgetExpenditureAmount":0,"budgetIncomeAmount":0,"expenditureAmount":0,"incomeAmount":0}],"paragraphs":[],"budgetExpenditureAmount":0,"expenditureAmount":0,"budgetIncomeAmount":0,"incomeAmount":0,"__v":0},{"gps":null,"_id":"5c6ced2642dd8914f1fdb1dd","profile":"5971ca164e7b8d5ea27f0488","year":2018,"etl":"5acdd6b5166dcc46cbcf4786","srcId":"10576000000","name":"EU-Šablony ZŠ a MŠ Tusarova","items":[{"_id":"5c6ced2e42dd8914f1fdb868","id":"4137","budgetExpenditureAmount":0,"budgetIncomeAmount":0,"expenditureAmount":0,"incomeAmount":0}],"paragraphs":[],"budgetExpenditureAmount":0,"expenditureAmount":0,"budgetIncomeAmount":0,"incomeAmount":0,"__v":0},{"gps":null,"_id":"5c6ced2642dd8914f1fdb1de","profile":"5971ca164e7b8d5ea27f0488","year":2018,"etl":"5acdd6b5166dcc46cbcf4786","srcId":"2017","name":"Smlouva nadační fond","items":[],"paragraphs":[{"_id":"5c6ced2e42dd8914f1fdb86a","id":"4399","budgetExpenditureAmount":18000,"expenditureAmount":18000}],"budgetExpenditureAmount":18000,"expenditureAmount":18000,"budgetIncomeAmount":0,"incomeAmount":0,"__v":0},{"gps":null,"_id":"5c6ced2642dd8914f1fdb1df","profile":"5971ca164e7b8d5ea27f0488","year":2018,"etl":"5acdd6b5166dcc46cbcf4786","srcId":"524018","name":"ZŠ Korunovační - studie využitelnosti půdy","items":[],"paragraphs":[{"_id":"5c6ced2e42dd8914f1fdb86c","id":"3113","budgetExpenditureAmount":108900,"expenditureAmount":108900}],"budgetExpenditureAmount":108900,"expenditureAmount":108900,"budgetIncomeAmount":0,"incomeAmount":0,"__v":0},{"gps":null,"_id":"5c6ced2642dd8914f1fdb203","profile":"5971ca164e7b8d5ea27f0488","year":2018,"etl":"5acdd6b5166dcc46cbcf4786","srcId":"388015","name":"Projekt a provoz přívozu","items":[],"paragraphs":[{"_id":"5c6ced2e42dd8914f1fdb86e","id":"2239","budgetExpenditureAmount":636000,"expenditureAmount":635940.2200000001}],"budgetExpenditureAmount":636000,"expenditureAmount":635940.2200000001,"budgetIncomeAmount":0,"incomeAmount":0,"__v":0},{"gps":null,"_id":"5c6ced2642dd8914f1fdb206","profile":"5971ca164e7b8d5ea27f0488","year":2018,"etl":"5acdd6b5166dcc46cbcf4786","srcId":"420016","name":"Půdní vestavba bytů U Uranie 5","items":[],"paragraphs":[{"_id":"5c6ced2e42dd8914f1fdb870","id":"3612","budgetExpenditureAmount":592800,"expenditureAmount":456046}],"budgetExpenditureAmount":592800,"expenditureAmount":456046,"budgetIncomeAmount":0,"incomeAmount":0,"__v":0},{"gps":null,"_id":"5c6ced2642dd8914f1fdb20f","profile":"5971ca164e7b8d5ea27f0488","year":2018,"etl":"5acdd6b5166dcc46cbcf4786","srcId":"503017","name":"Revitalizace  ul. Fr. Křížka","items":[],"paragraphs":[{"_id":"5c6ced2e42dd8914f1fdb873","id":"3699","budgetExpenditureAmount":794700,"expenditureAmount":543102.15},{"_id":"5c6ced2e42dd8914f1fdb872","id":"2219","budgetExpenditureAmount":2550000,"expenditureAmount":0}],"budgetExpenditureAmount":3344700,"expenditureAmount":543102.15,"budgetIncomeAmount":0,"incomeAmount":0,"__v":0},{"gps":null,"_id":"5c6ced2642dd8914f1fdb24b","profile":"5971ca164e7b8d5ea27f0488","year":2018,"etl":"5acdd6b5166dcc46cbcf4786","srcId":"79816","name":"nespecifik. sport 2016","items":[],"paragraphs":[{"_id":"5c6ced2e42dd8914f1fdb876","id":"3419","budgetExpenditureAmount":175000,"expenditureAmount":68000},{"_id":"5c6ced2e42dd8914f1fdb875","id":"3119","budgetExpenditureAmount":0,"expenditureAmount":0}],"budgetExpenditureAmount":175000,"expenditureAmount":68000,"budgetIncomeAmount":0,"incomeAmount":0,"__v":0},{"gps":null,"_id":"5c6ced2642dd8914f1fdb25a","profile":"5971ca164e7b8d5ea27f0488","year":2018,"etl":"5acdd6b5166dcc46cbcf4786","srcId":"516018","name":"ZŠ Fr. Plamínkové - reko kuchyně - výměna oken","items":[],"paragraphs":[{"_id":"5c6ced2e42dd8914f1fdb878","id":"3113","budgetExpenditureAmount":1700000,"expenditureAmount":13915}],"budgetExpenditureAmount":1700000,"expenditureAmount":13915,"budgetIncomeAmount":0,"incomeAmount":0,"__v":0},{"gps":null,"_id":"5c6ced2642dd8914f1fdb25c","profile":"5971ca164e7b8d5ea27f0488","year":2018,"etl":"5acdd6b5166dcc46cbcf4786","srcId":"518018","name":"MŠ Na Výšinách - reko gastroprovozu a elektroroz","items":[],"paragraphs":[{"_id":"5c6ced2e42dd8914f1fdb87a","id":"3111","budgetExpenditureAmount":1240000,"expenditureAmount":620730}],"budgetExpenditureAmount":1240000,"expenditureAmount":620730,"budgetIncomeAmount":0,"incomeAmount":0,"__v":0},{"gps":null,"_id":"5c6ced2742dd8914f1fdb26b","profile":"5971ca164e7b8d5ea27f0488","year":2018,"etl":"5acdd6b5166dcc46cbcf4786","srcId":"32017","name":"akce  \"Nejlepší na Sedmičce\"","items":[],"paragraphs":[{"_id":"5c6ced2e42dd8914f1fdb87c","id":"3900","budgetExpenditureAmount":55000,"expenditureAmount":48065}],"budgetExpenditureAmount":55000,"expenditureAmount":48065,"budgetIncomeAmount":0,"incomeAmount":0,"__v":0},{"gps":null,"_id":"5c6ced2742dd8914f1fdb271","profile":"5971ca164e7b8d5ea27f0488","year":2018,"etl":"5acdd6b5166dcc46cbcf4786","srcId":"80633507017","name":"Reko obj. Dobrovského 19/537","items":[],"paragraphs":[{"_id":"5c6ced2e42dd8914f1fdb87e","id":"3612","budgetExpenditureAmount":28880100,"expenditureAmount":656600}],"budgetExpenditureAmount":28880100,"expenditureAmount":656600,"budgetIncomeAmount":0,"incomeAmount":0,"__v":0},{"gps":null,"_id":"5c6ced2742dd8914f1fdb290","profile":"5971ca164e7b8d5ea27f0488","year":2018,"etl":"5acdd6b5166dcc46cbcf4786","srcId":"463017","name":"Reko DH Ortenovo nám.","items":[],"paragraphs":[{"_id":"5c6ced2e42dd8914f1fdb880","id":"3421","budgetExpenditureAmount":250000,"expenditureAmount":169400}],"budgetExpenditureAmount":250000,"expenditureAmount":169400,"budgetIncomeAmount":0,"incomeAmount":0,"__v":0},{"gps":null,"_id":"5c6ced2742dd8914f1fdb298","profile":"5971ca164e7b8d5ea27f0488","year":2018,"etl":"5acdd6b5166dcc46cbcf4786","srcId":"521018","name":"MŠ Nad Štolou - reko umýváren","items":[],"paragraphs":[{"_id":"5c6ced2e42dd8914f1fdb882","id":"3111","budgetExpenditureAmount":10000,"expenditureAmount":9680}],"budgetExpenditureAmount":10000,"expenditureAmount":9680,"budgetIncomeAmount":0,"incomeAmount":0,"__v":0},{"gps":null,"_id":"5c6ced2742dd8914f1fdb2d3","profile":"5971ca164e7b8d5ea27f0488","year":2018,"etl":"5acdd6b5166dcc46cbcf4786","srcId":"493017","name":"ZŠ Tusarova  - zateplení  tělocvičny","items":[],"paragraphs":[{"_id":"5c6ced2e42dd8914f1fdb884","id":"3113","budgetExpenditureAmount":1300000,"expenditureAmount":605685}],"budgetExpenditureAmount":1300000,"expenditureAmount":605685,"budgetIncomeAmount":0,"incomeAmount":0,"__v":0},{"gps":null,"_id":"5c6ced2742dd8914f1fdb2ea","profile":"5971ca164e7b8d5ea27f0488","year":2018,"etl":"5acdd6b5166dcc46cbcf4786","srcId":"10491000000","name":"Šablony pro MŠ a ZŠ I","items":[{"_id":"5c6ced2e42dd8914f1fdb886","id":"4137","budgetExpenditureAmount":0,"budgetIncomeAmount":0,"expenditureAmount":0,"incomeAmount":0}],"paragraphs":[],"budgetExpenditureAmount":0,"expenditureAmount":0,"budgetIncomeAmount":0,"incomeAmount":0,"__v":0},{"gps":null,"_id":"5c6ced2742dd8914f1fdb2eb","profile":"5971ca164e7b8d5ea27f0488","year":2018,"etl":"5acdd6b5166dcc46cbcf4786","srcId":"10491000301","name":"MŠ Kostelní - šablony pro MŠ","items":[{"_id":"5c6ced2e42dd8914f1fdb888","id":"4137","budgetExpenditureAmount":0,"budgetIncomeAmount":227400,"expenditureAmount":0,"incomeAmount":227356.8}],"paragraphs":[{"_id":"5c6ced2e42dd8914f1fdb889","id":"3111","budgetExpenditureAmount":227400,"expenditureAmount":227356.8}],"budgetExpenditureAmount":227400,"expenditureAmount":227356.8,"budgetIncomeAmount":227400,"incomeAmount":227356.8,"__v":0},{"gps":null,"_id":"5c6ced2742dd8914f1fdb2fe","profile":"5971ca164e7b8d5ea27f0488","year":2018,"etl":"5acdd6b5166dcc46cbcf4786","srcId":"201800","name":"Projekty v soc. oblasti","items":[],"paragraphs":[{"_id":"5c6ced2e42dd8914f1fdb88b","id":"4399","budgetExpenditureAmount":1300000,"expenditureAmount":217514}],"budgetExpenditureAmount":1300000,"expenditureAmount":217514,"budgetIncomeAmount":0,"incomeAmount":0,"__v":0},{"gps":null,"_id":"5c6ced2842dd8914f1fdb32c","profile":"5971ca164e7b8d5ea27f0488","year":2018,"etl":"5acdd6b5166dcc46cbcf4786","srcId":"2370310000321","name":"OPP-pól růstu ZŠ Strossm.- Jsme IN","items":[{"_id":"5c6ced2e42dd8914f1fdb88d","id":"4137","budgetExpenditureAmount":0,"budgetIncomeAmount":1469200,"expenditureAmount":0,"incomeAmount":1469200}],"paragraphs":[{"_id":"5c6ced2e42dd8914f1fdb88e","id":"3113","budgetExpenditureAmount":1469200,"expenditureAmount":1469200}],"budgetExpenditureAmount":1469200,"expenditureAmount":1469200,"budgetIncomeAmount":1469200,"incomeAmount":1469200,"__v":0},{"gps":null,"_id":"5c6ced2842dd8914f1fdb33e","profile":"5971ca164e7b8d5ea27f0488","year":2018,"etl":"5acdd6b5166dcc46cbcf4786","srcId":"516","name":"Poštovné OSZ","items":[],"paragraphs":[{"_id":"5c6ced2e42dd8914f1fdb890","id":"4399","budgetExpenditureAmount":0,"expenditureAmount":0}],"budgetExpenditureAmount":0,"expenditureAmount":0,"budgetIncomeAmount":0,"incomeAmount":0,"__v":0},{"gps":null,"_id":"5c6ced2842dd8914f1fdb342","profile":"5971ca164e7b8d5ea27f0488","year":2018,"etl":"5acdd6b5166dcc46cbcf4786","srcId":"7011","name":"dotace HMP4000 -Bezpečné prázdniny","items":[],"paragraphs":[{"_id":"5c6ced2e42dd8914f1fdb892","id":"5399","budgetExpenditureAmount":85000,"expenditureAmount":85000}],"budgetExpenditureAmount":85000,"expenditureAmount":85000,"budgetIncomeAmount":0,"incomeAmount":0,"__v":0},{"gps":null,"_id":"5c6ced2842dd8914f1fdb34e","profile":"5971ca164e7b8d5ea27f0488","year":2018,"etl":"5acdd6b5166dcc46cbcf4786","srcId":"7560","name":"Invest. transfer pro TSK hl.m.Prahy- chodní.pro.g","items":[],"paragraphs":[{"_id":"5c6ced2e42dd8914f1fdb894","id":"6330","budgetExpenditureAmount":0,"expenditureAmount":0}],"budgetExpenditureAmount":0,"expenditureAmount":0,"budgetIncomeAmount":0,"incomeAmount":0,"__v":0},{"gps":null,"_id":"5c6ced2842dd8914f1fdb34f","profile":"5971ca164e7b8d5ea27f0488","year":2018,"etl":"5acdd6b5166dcc46cbcf4786","srcId":"7560000000","name":"Odvod pro TSK hl.m.Prahu - chodníkový program","items":[],"paragraphs":[{"_id":"5c6ced2e42dd8914f1fdb896","id":"6330","budgetExpenditureAmount":16197100,"expenditureAmount":16197092.84}],"budgetExpenditureAmount":16197100,"expenditureAmount":16197092.84,"budgetIncomeAmount":0,"incomeAmount":0,"__v":0},{"gps":null,"_id":"5c6ced2842dd8914f1fdb350","profile":"5971ca164e7b8d5ea27f0488","year":2018,"etl":"5acdd6b5166dcc46cbcf4786","srcId":"10576000326","name":"EU-Šablony ZŠ a MŠ Tusarova","items":[{"_id":"5c6ced2e42dd8914f1fdb898","id":"4137","budgetExpenditureAmount":0,"budgetIncomeAmount":655000,"expenditureAmount":0,"incomeAmount":655009.6}],"paragraphs":[{"_id":"5c6ced2e42dd8914f1fdb899","id":"3113","budgetExpenditureAmount":655000,"expenditureAmount":655009.6}],"budgetExpenditureAmount":655000,"expenditureAmount":655009.6,"budgetIncomeAmount":655000,"incomeAmount":655009.6,"__v":0},{"gps":null,"_id":"5c6ced2842dd8914f1fdb351","profile":"5971ca164e7b8d5ea27f0488","year":2018,"etl":"5acdd6b5166dcc46cbcf4786","srcId":"10446000322","name":"Šablony pro MŠ a ZŠ I - projekt zjednodušeného vyk","items":[{"_id":"5c6ced2e42dd8914f1fdb89b","id":"4137","budgetExpenditureAmount":0,"budgetIncomeAmount":381800,"expenditureAmount":0,"incomeAmount":381747.6}],"paragraphs":[{"_id":"5c6ced2e42dd8914f1fdb89c","id":"3113","budgetExpenditureAmount":381800,"expenditureAmount":381747.6}],"budgetExpenditureAmount":381800,"expenditureAmount":381747.6,"budgetIncomeAmount":381800,"incomeAmount":381747.6,"__v":0},{"gps":null,"_id":"5c6ced2842dd8914f1fdb35b","profile":"5971ca164e7b8d5ea27f0488","year":2018,"etl":"5acdd6b5166dcc46cbcf4786","srcId":"55","name":"ZAHRANICNI CESTY","items":[],"paragraphs":[{"_id":"5c6ced2e42dd8914f1fdb89e","id":"6171","budgetExpenditureAmount":0,"expenditureAmount":0}],"budgetExpenditureAmount":0,"expenditureAmount":0,"budgetIncomeAmount":0,"incomeAmount":0,"__v":0},{"gps":null,"_id":"5c6ced2842dd8914f1fdb36a","profile":"5971ca164e7b8d5ea27f0488","year":2018,"etl":"5acdd6b5166dcc46cbcf4786","srcId":"10660000302","name":"MŠ U Uranie - šablony pro MŠ ze SR","items":[{"_id":"5c6ced2e42dd8914f1fdb8a0","id":"4137","budgetExpenditureAmount":0,"budgetIncomeAmount":294400,"expenditureAmount":0,"incomeAmount":294403.2}],"paragraphs":[{"_id":"5c6ced2e42dd8914f1fdb8a1","id":"3111","budgetExpenditureAmount":294400,"expenditureAmount":294403.2}],"budgetExpenditureAmount":294400,"expenditureAmount":294403.2,"budgetIncomeAmount":294400,"incomeAmount":294403.2,"__v":0},{"gps":null,"_id":"5c6ced2842dd8914f1fdb36b","profile":"5971ca164e7b8d5ea27f0488","year":2018,"etl":"5acdd6b5166dcc46cbcf4786","srcId":"10577000325","name":"EU-Šablony ZŠ  Fr. Plamínkové","items":[{"_id":"5c6ced2e42dd8914f1fdb8a3","id":"4137","budgetExpenditureAmount":0,"budgetIncomeAmount":459000,"expenditureAmount":0,"incomeAmount":458983.6}],"paragraphs":[{"_id":"5c6ced2e42dd8914f1fdb8a4","id":"3113","budgetExpenditureAmount":459000,"expenditureAmount":458983.6}],"budgetExpenditureAmount":459000,"expenditureAmount":458983.6,"budgetIncomeAmount":459000,"incomeAmount":458983.6,"__v":0},{"gps":null,"_id":"5c6ced2842dd8914f1fdb386","profile":"5971ca164e7b8d5ea27f0488","year":2018,"etl":"5acdd6b5166dcc46cbcf4786","srcId":"475017","name":"Reko soklu ZŠ Korunovační","items":[],"paragraphs":[{"_id":"5c6ced2e42dd8914f1fdb8a6","id":"3113","budgetExpenditureAmount":1400000,"expenditureAmount":147274}],"budgetExpenditureAmount":1400000,"expenditureAmount":147274,"budgetIncomeAmount":0,"incomeAmount":0,"__v":0},{"gps":null,"_id":"5c6ced2842dd8914f1fdb387","profile":"5971ca164e7b8d5ea27f0488","year":2018,"etl":"5acdd6b5166dcc46cbcf4786","srcId":"519018","name":"MŠ Visionary - interiér a gastro zařízení","items":[],"paragraphs":[{"_id":"5c6ced2e42dd8914f1fdb8a8","id":"3111","budgetExpenditureAmount":1735000,"expenditureAmount":1734914.2}],"budgetExpenditureAmount":1735000,"expenditureAmount":1734914.2,"budgetIncomeAmount":0,"incomeAmount":0,"__v":0},{"gps":null,"_id":"5c6ced2842dd8914f1fdb38b","profile":"5971ca164e7b8d5ea27f0488","year":2018,"etl":"5acdd6b5166dcc46cbcf4786","srcId":"224","name":"POSTOVNE VAKUS","items":[{"_id":"5c6ced2e42dd8914f1fdb8aa","id":"2328","budgetExpenditureAmount":0,"budgetIncomeAmount":0,"expenditureAmount":0,"incomeAmount":-200}],"paragraphs":[],"budgetExpenditureAmount":0,"expenditureAmount":0,"budgetIncomeAmount":0,"incomeAmount":-200,"__v":0},{"gps":null,"_id":"5c6ced2942dd8914f1fdb3b4","profile":"5971ca164e7b8d5ea27f0488","year":2018,"etl":"5acdd6b5166dcc46cbcf4786","srcId":"523018","name":"Zaměření objektů ZŠ a MŠ - pasportizace","items":[],"paragraphs":[{"_id":"5c6ced2e42dd8914f1fdb8ac","id":"3113","budgetExpenditureAmount":800000,"expenditureAmount":363000}],"budgetExpenditureAmount":800000,"expenditureAmount":363000,"budgetIncomeAmount":0,"incomeAmount":0,"__v":0},{"gps":null,"_id":"5c6ced2942dd8914f1fdb3e4","profile":"5971ca164e7b8d5ea27f0488","year":2018,"etl":"5acdd6b5166dcc46cbcf4786","srcId":"522018","name":"MŠ Janovského - výměna kotlů a kouřovodu","items":[],"paragraphs":[{"_id":"5c6ced2e42dd8914f1fdb8ae","id":"3111","budgetExpenditureAmount":550000,"expenditureAmount":534793}],"budgetExpenditureAmount":550000,"expenditureAmount":534793,"budgetIncomeAmount":0,"incomeAmount":0,"__v":0},{"gps":null,"_id":"5c6ced2a42dd8914f1fdb429","profile":"5971ca164e7b8d5ea27f0488","year":2018,"etl":"5acdd6b5166dcc46cbcf4786","srcId":"821","name":"SFP Zařízení - posilovna","items":[],"paragraphs":[{"_id":"5c6ced2e42dd8914f1fdb8b0","id":"6171","budgetExpenditureAmount":6500,"expenditureAmount":6480}],"budgetExpenditureAmount":6500,"expenditureAmount":6480,"budgetIncomeAmount":0,"incomeAmount":0,"__v":0},{"gps":null,"_id":"5c6ced2a42dd8914f1fdb437","profile":"5971ca164e7b8d5ea27f0488","year":2018,"etl":"5acdd6b5166dcc46cbcf4786","srcId":"2360519000321","name":"OPP-pól růstu Moderniz učeben  ZŠ Strossma","items":[{"_id":"5c6ced2e42dd8914f1fdb8b2","id":"4137","budgetExpenditureAmount":0,"budgetIncomeAmount":2089800,"expenditureAmount":0,"incomeAmount":1044000}],"paragraphs":[{"_id":"5c6ced2e42dd8914f1fdb8b3","id":"3113","budgetExpenditureAmount":4266600,"expenditureAmount":1212900}],"budgetExpenditureAmount":4266600,"expenditureAmount":1212900,"budgetIncomeAmount":2089800,"incomeAmount":1044000,"__v":0},{"gps":null,"_id":"5c6ced2a42dd8914f1fdb47a","profile":"5971ca164e7b8d5ea27f0488","year":2018,"etl":"5acdd6b5166dcc46cbcf4786","srcId":"80687508017","name":"Reko víceúčel. sport. hřiště a vyb. záz. Jateční","items":[],"paragraphs":[{"_id":"5c6ced2e42dd8914f1fdb8b5","id":"3421","budgetExpenditureAmount":0,"expenditureAmount":3600000}],"budgetExpenditureAmount":0,"expenditureAmount":3600000,"budgetIncomeAmount":0,"incomeAmount":0,"__v":0},{"gps":null,"_id":"5c6ced2a42dd8914f1fdb47b","profile":"5971ca164e7b8d5ea27f0488","year":2018,"etl":"5acdd6b5166dcc46cbcf4786","srcId":"2390459501017","name":"OPP - pól růstu navýš.kapac.zák.vzděl. soc.inkluze","items":[],"paragraphs":[{"_id":"5c6ced2e42dd8914f1fdb8b7","id":"3113","budgetExpenditureAmount":1925300,"expenditureAmount":-25000}],"budgetExpenditureAmount":1925300,"expenditureAmount":-25000,"budgetIncomeAmount":0,"incomeAmount":0,"__v":0},{"gps":null,"_id":"5c6ced2b42dd8914f1fdb4e6","profile":"5971ca164e7b8d5ea27f0488","year":2018,"etl":"5acdd6b5166dcc46cbcf4786","srcId":"513018","name":"ZŠ TGM reko podlah","items":[],"paragraphs":[{"_id":"5c6ced2e42dd8914f1fdb8b9","id":"3113","budgetExpenditureAmount":100000,"expenditureAmount":48400}],"budgetExpenditureAmount":100000,"expenditureAmount":48400,"budgetIncomeAmount":0,"incomeAmount":0,"__v":0},{"gps":null,"_id":"5c6ced2b42dd8914f1fdb4f6","profile":"5971ca164e7b8d5ea27f0488","year":2018,"etl":"5acdd6b5166dcc46cbcf4786","srcId":"512018","name":"ZŠ TGM reko půdního prostoru - boční křídla","items":[],"paragraphs":[{"_id":"5c6ced2e42dd8914f1fdb8bb","id":"3113","budgetExpenditureAmount":2420000,"expenditureAmount":847000}],"budgetExpenditureAmount":2420000,"expenditureAmount":847000,"budgetIncomeAmount":0,"incomeAmount":0,"__v":0},{"gps":null,"_id":"5c6ced2b42dd8914f1fdb536","profile":"5971ca164e7b8d5ea27f0488","year":2018,"etl":"5acdd6b5166dcc46cbcf4786","srcId":"50111","name":"Dotace HMP - Už si rozumíme","items":[],"paragraphs":[{"_id":"5c6ced2e42dd8914f1fdb8bd","id":"4342","budgetExpenditureAmount":150000,"expenditureAmount":150000}],"budgetExpenditureAmount":150000,"expenditureAmount":150000,"budgetIncomeAmount":0,"incomeAmount":0,"__v":0},{"gps":null,"_id":"5c6ced2c42dd8914f1fdb550","profile":"5971ca164e7b8d5ea27f0488","year":2018,"etl":"5acdd6b5166dcc46cbcf4786","srcId":"811","name":"KULTURNI AKCE","items":[],"paragraphs":[{"_id":"5c6ced2e42dd8914f1fdb8bf","id":"6171","budgetExpenditureAmount":40000,"expenditureAmount":40000}],"budgetExpenditureAmount":40000,"expenditureAmount":40000,"budgetIncomeAmount":0,"incomeAmount":0,"__v":0},{"gps":null,"_id":"5c6ced2c42dd8914f1fdb558","profile":"5971ca164e7b8d5ea27f0488","year":2018,"etl":"5acdd6b5166dcc46cbcf4786","srcId":"10668000000","name":"Školní obědy dostupné pro každé dítě II","items":[{"_id":"5c6ced2e42dd8914f1fdb8c1","id":"2229","budgetExpenditureAmount":0,"budgetIncomeAmount":444000,"expenditureAmount":0,"incomeAmount":443974.92}],"paragraphs":[{"_id":"5c6ced2e42dd8914f1fdb8c4","id":"6330","budgetExpenditureAmount":444000,"expenditureAmount":443974.92},{"_id":"5c6ced2e42dd8914f1fdb8c3","id":"3111","budgetExpenditureAmount":0,"expenditureAmount":0},{"_id":"5c6ced2e42dd8914f1fdb8c2","id":"3113","budgetExpenditureAmount":0,"expenditureAmount":0}],"budgetExpenditureAmount":444000,"expenditureAmount":443974.92,"budgetIncomeAmount":444000,"incomeAmount":443974.92,"__v":0},{"gps":null,"_id":"5c6ced2c42dd8914f1fdb572","profile":"5971ca164e7b8d5ea27f0488","year":2018,"etl":"5acdd6b5166dcc46cbcf4786","srcId":"7012","name":"dotace HMP  P/7 bezpečně online","items":[],"paragraphs":[{"_id":"5c6ced2e42dd8914f1fdb8c6","id":"5399","budgetExpenditureAmount":70000,"expenditureAmount":70000}],"budgetExpenditureAmount":70000,"expenditureAmount":70000,"budgetIncomeAmount":0,"incomeAmount":0,"__v":0},{"gps":null,"_id":"5c6ced2c42dd8914f1fdb582","profile":"5971ca164e7b8d5ea27f0488","year":2018,"etl":"5acdd6b5166dcc46cbcf4786","srcId":"10772000000","name":"EU-Šablony FMŠ Na Výšinách","items":[{"_id":"5c6ced2e42dd8914f1fdb8c9","id":"4131","budgetExpenditureAmount":0,"budgetIncomeAmount":0,"expenditureAmount":0,"incomeAmount":0},{"_id":"5c6ced2e42dd8914f1fdb8c8","id":"4137","budgetExpenditureAmount":0,"budgetIncomeAmount":238600,"expenditureAmount":0,"incomeAmount":238568}],"paragraphs":[],"budgetExpenditureAmount":0,"expenditureAmount":0,"budgetIncomeAmount":238600,"incomeAmount":238568,"__v":0},{"gps":null,"_id":"5c6ced2c42dd8914f1fdb583","profile":"5971ca164e7b8d5ea27f0488","year":2018,"etl":"5acdd6b5166dcc46cbcf4786","srcId":"10736000000","name":"dotace HMP - Šablony pro ZŠ Strossmayerovo nám","items":[{"_id":"5c6ced2e42dd8914f1fdb8cc","id":"4131","budgetExpenditureAmount":0,"budgetIncomeAmount":0,"expenditureAmount":0,"incomeAmount":0},{"_id":"5c6ced2e42dd8914f1fdb8cb","id":"4137","budgetExpenditureAmount":0,"budgetIncomeAmount":637000,"expenditureAmount":0,"incomeAmount":636964.8}],"paragraphs":[],"budgetExpenditureAmount":0,"expenditureAmount":0,"budgetIncomeAmount":637000,"incomeAmount":636964.8,"__v":0},{"gps":null,"_id":"5c6ced2d42dd8914f1fdb5a6","profile":"5971ca164e7b8d5ea27f0488","year":2018,"etl":"5acdd6b5166dcc46cbcf4786","srcId":"10631000000","name":"OPZ EU-Ověření  implementace  soc.bydlení","items":[{"_id":"5c6ced2e42dd8914f1fdb8ce","id":"4137","budgetExpenditureAmount":0,"budgetIncomeAmount":1066200,"expenditureAmount":0,"incomeAmount":1066180.2}],"paragraphs":[],"budgetExpenditureAmount":0,"expenditureAmount":0,"budgetIncomeAmount":1066200,"incomeAmount":1066180.2,"__v":0},{"gps":null,"_id":"5c6ced2d42dd8914f1fdb5bc","profile":"5971ca164e7b8d5ea27f0488","year":2018,"etl":"5acdd6b5166dcc46cbcf4786","srcId":"348014","name":"Obnova veř.osv.a vod.prvku - Řezáč.nám","items":[],"paragraphs":[{"_id":"5c6ced2e42dd8914f1fdb8d0","id":"3745","budgetExpenditureAmount":600000,"expenditureAmount":558543}],"budgetExpenditureAmount":600000,"expenditureAmount":558543,"budgetIncomeAmount":0,"incomeAmount":0,"__v":0},{"gps":null,"_id":"5c6ced2d42dd8914f1fdb5df","profile":"5971ca164e7b8d5ea27f0488","year":2018,"etl":"5acdd6b5166dcc46cbcf4786","srcId":"10772000316","name":"Dotace z HMP - Šablony pro MŠ Na Výšinách","items":[],"paragraphs":[{"_id":"5c6ced2e42dd8914f1fdb8d2","id":"3111","budgetExpenditureAmount":238600,"expenditureAmount":238568}],"budgetExpenditureAmount":238600,"expenditureAmount":238568,"budgetIncomeAmount":0,"incomeAmount":0,"__v":0},{"gps":null,"_id":"5c6ced2d42dd8914f1fdb5e1","profile":"5971ca164e7b8d5ea27f0488","year":2018,"etl":"5acdd6b5166dcc46cbcf4786","srcId":"10736000321","name":"dotace HMP -  Šablony ZŠ Strossm.nám","items":[],"paragraphs":[{"_id":"5c6ced2e42dd8914f1fdb8d4","id":"3113","budgetExpenditureAmount":637000,"expenditureAmount":636964.8}],"budgetExpenditureAmount":637000,"expenditureAmount":636964.8,"budgetIncomeAmount":0,"incomeAmount":0,"__v":0},{"gps":null,"_id":"5c6ced2e42dd8914f1fdb671","profile":"5971ca164e7b8d5ea27f0488","year":2018,"etl":"5acdd6b5166dcc46cbcf4786","srcId":"510018","name":"Reko zeleně U vody","items":[],"paragraphs":[{"_id":"5c6ced2e42dd8914f1fdb8d6","id":"3745","budgetExpenditureAmount":500000,"expenditureAmount":0}],"budgetExpenditureAmount":500000,"expenditureAmount":0,"budgetIncomeAmount":0,"incomeAmount":0,"__v":0},{"gps":null,"_id":"5c6ced2e42dd8914f1fdb672","profile":"5971ca164e7b8d5ea27f0488","year":2018,"etl":"5acdd6b5166dcc46cbcf4786","srcId":"465017","name":"Park Tusarova","items":[],"paragraphs":[{"_id":"5c6ced2e42dd8914f1fdb8d8","id":"3421","budgetExpenditureAmount":210900,"expenditureAmount":0}],"budgetExpenditureAmount":210900,"expenditureAmount":0,"budgetIncomeAmount":0,"incomeAmount":0,"__v":0},{"gps":null,"_id":"5c6ced2e42dd8914f1fdb673","profile":"5971ca164e7b8d5ea27f0488","year":2018,"etl":"5acdd6b5166dcc46cbcf4786","srcId":"80559504017","name":"Inv. dotace vybudování Fitparku","items":[],"paragraphs":[{"_id":"5c6ced2e42dd8914f1fdb8da","id":"3412","budgetExpenditureAmount":600000,"expenditureAmount":0}],"budgetExpenditureAmount":600000,"expenditureAmount":0,"budgetIncomeAmount":0,"incomeAmount":0,"__v":0},{"gps":null,"_id":"5c6ced2e42dd8914f1fdb674","profile":"5971ca164e7b8d5ea27f0488","year":2018,"etl":"5acdd6b5166dcc46cbcf4786","srcId":"412016","name":"Nákup nádob na BRKO","items":[],"paragraphs":[{"_id":"5c6ced2e42dd8914f1fdb8dc","id":"3722","budgetExpenditureAmount":0,"expenditureAmount":0}],"budgetExpenditureAmount":0,"expenditureAmount":0,"budgetIncomeAmount":0,"incomeAmount":0,"__v":0},{"gps":null,"_id":"5c6ced2e42dd8914f1fdb675","profile":"5971ca164e7b8d5ea27f0488","year":2018,"etl":"5acdd6b5166dcc46cbcf4786","srcId":"408015","name":"Dar MIA FILM","items":[],"paragraphs":[{"_id":"5c6ced2e42dd8914f1fdb8de","id":"2219","budgetExpenditureAmount":130000,"expenditureAmount":0}],"budgetExpenditureAmount":130000,"expenditureAmount":0,"budgetIncomeAmount":0,"incomeAmount":0,"__v":0},{"gps":null,"_id":"5c6ced2e42dd8914f1fdb676","profile":"5971ca164e7b8d5ea27f0488","year":2018,"etl":"5acdd6b5166dcc46cbcf4786","srcId":"131107","name":"Chodníkový program TSK","items":[],"paragraphs":[{"_id":"5c6ced2e42dd8914f1fdb8e0","id":"2219","budgetExpenditureAmount":6102900,"expenditureAmount":0}],"budgetExpenditureAmount":6102900,"expenditureAmount":0,"budgetIncomeAmount":0,"incomeAmount":0,"__v":0},{"gps":null,"_id":"5c6ced2e42dd8914f1fdb677","profile":"5971ca164e7b8d5ea27f0488","year":2018,"etl":"5acdd6b5166dcc46cbcf4786","srcId":"505017","name":"Navýšení rozp. akce Chodníkový program TSK","items":[],"paragraphs":[{"_id":"5c6ced2e42dd8914f1fdb8e2","id":"2219","budgetExpenditureAmount":0,"expenditureAmount":0}],"budgetExpenditureAmount":0,"expenditureAmount":0,"budgetIncomeAmount":0,"incomeAmount":0,"__v":0},{"gps":null,"_id":"5c6ced2e42dd8914f1fdb678","profile":"5971ca164e7b8d5ea27f0488","year":2018,"etl":"5acdd6b5166dcc46cbcf4786","srcId":"506017","name":"Přeměna  ulice Antonínská","items":[],"paragraphs":[{"_id":"5c6ced2e42dd8914f1fdb8e4","id":"2219","budgetExpenditureAmount":1000000,"expenditureAmount":0}],"budgetExpenditureAmount":1000000,"expenditureAmount":0,"budgetIncomeAmount":0,"incomeAmount":0,"__v":0},{"gps":null,"_id":"5c6ced2e42dd8914f1fdb679","profile":"5971ca164e7b8d5ea27f0488","year":2018,"etl":"5acdd6b5166dcc46cbcf4786","srcId":"511018","name":"ul. Kostelní - revitalizace hlíd. park. a okolí","items":[],"paragraphs":[{"_id":"5c6ced2e42dd8914f1fdb8e6","id":"2219","budgetExpenditureAmount":500000,"expenditureAmount":0}],"budgetExpenditureAmount":500000,"expenditureAmount":0,"budgetIncomeAmount":0,"incomeAmount":0,"__v":0},{"gps":null,"_id":"5c6ced2e42dd8914f1fdb67a","profile":"5971ca164e7b8d5ea27f0488","year":2018,"etl":"5acdd6b5166dcc46cbcf4786","srcId":"80236455016","name":"Revitalizace  ulice Ovenecká","items":[],"paragraphs":[{"_id":"5c6ced2e42dd8914f1fdb8e8","id":"2219","budgetExpenditureAmount":11000000,"expenditureAmount":0}],"budgetExpenditureAmount":11000000,"expenditureAmount":0,"budgetIncomeAmount":0,"incomeAmount":0,"__v":0},{"gps":null,"_id":"5c6ced2e42dd8914f1fdb67b","profile":"5971ca164e7b8d5ea27f0488","year":2018,"etl":"5acdd6b5166dcc46cbcf4786","srcId":"80310458016","name":"Reko výpustí v ul. Jana Zajíce","items":[],"paragraphs":[{"_id":"5c6ced2e42dd8914f1fdb8ea","id":"2219","budgetExpenditureAmount":0,"expenditureAmount":0}],"budgetExpenditureAmount":0,"expenditureAmount":0,"budgetIncomeAmount":0,"incomeAmount":0,"__v":0},{"gps":null,"_id":"5c6ced2e42dd8914f1fdb67c","profile":"5971ca164e7b8d5ea27f0488","year":2018,"etl":"5acdd6b5166dcc46cbcf4786","srcId":"80311459016","name":"Reko chodníků v ul. Janovského","items":[],"paragraphs":[{"_id":"5c6ced2e42dd8914f1fdb8ec","id":"2219","budgetExpenditureAmount":12000000,"expenditureAmount":0}],"budgetExpenditureAmount":12000000,"expenditureAmount":0,"budgetIncomeAmount":0,"incomeAmount":0,"__v":0},{"gps":null,"_id":"5c6ced2e42dd8914f1fdb67d","profile":"5971ca164e7b8d5ea27f0488","year":2018,"etl":"5acdd6b5166dcc46cbcf4786","srcId":"2015","name":"Nevyčerp.přísp. v r. 2015 na Výkon pěstounské péče","items":[],"paragraphs":[{"_id":"5c6ced2e42dd8914f1fdb8ee","id":"4339","budgetExpenditureAmount":0,"expenditureAmount":0}],"budgetExpenditureAmount":0,"expenditureAmount":0,"budgetIncomeAmount":0,"incomeAmount":0,"__v":0},{"gps":null,"_id":"5c6ced2e42dd8914f1fdb67e","profile":"5971ca164e7b8d5ea27f0488","year":2018,"etl":"5acdd6b5166dcc46cbcf4786","srcId":"2014","name":"2014","items":[],"paragraphs":[{"_id":"5c6ced2e42dd8914f1fdb8f0","id":"4399","budgetExpenditureAmount":694000,"expenditureAmount":0}],"budgetExpenditureAmount":694000,"expenditureAmount":0,"budgetIncomeAmount":0,"incomeAmount":0,"__v":0},{"gps":null,"_id":"5c6ced2e42dd8914f1fdb67f","profile":"5971ca164e7b8d5ea27f0488","year":2018,"etl":"5acdd6b5166dcc46cbcf4786","srcId":"488017","name":"ZŠ Strossmayerovo nám. - havarijní stav střechy","items":[],"paragraphs":[{"_id":"5c6ced2e42dd8914f1fdb8f2","id":"3113","budgetExpenditureAmount":100600,"expenditureAmount":0}],"budgetExpenditureAmount":100600,"expenditureAmount":0,"budgetIncomeAmount":0,"incomeAmount":0,"__v":0},{"gps":null,"_id":"5c6ced2e42dd8914f1fdb680","profile":"5971ca164e7b8d5ea27f0488","year":2018,"etl":"5acdd6b5166dcc46cbcf4786","srcId":"351014","name":"ZŠ Strossm.n.-budova-reko osv. a elektrorozvodů","items":[],"paragraphs":[{"_id":"5c6ced2e42dd8914f1fdb8f4","id":"3113","budgetExpenditureAmount":600000,"expenditureAmount":0}],"budgetExpenditureAmount":600000,"expenditureAmount":0,"budgetIncomeAmount":0,"incomeAmount":0,"__v":0},{"gps":null,"_id":"5c6ced2e42dd8914f1fdb681","profile":"5971ca164e7b8d5ea27f0488","year":2018,"etl":"5acdd6b5166dcc46cbcf4786","srcId":"461016","name":"ZŠ Korunovační - elektroinstalace","items":[],"paragraphs":[{"_id":"5c6ced2e42dd8914f1fdb8f6","id":"3113","budgetExpenditureAmount":1000000,"expenditureAmount":0}],"budgetExpenditureAmount":1000000,"expenditureAmount":0,"budgetIncomeAmount":0,"incomeAmount":0,"__v":0},{"gps":null,"_id":"5c6ced2e42dd8914f1fdb682","profile":"5971ca164e7b8d5ea27f0488","year":2018,"etl":"5acdd6b5166dcc46cbcf4786","srcId":"460016","name":"ZŠ Tussarova","items":[],"paragraphs":[{"_id":"5c6ced2e42dd8914f1fdb8f8","id":"3113","budgetExpenditureAmount":518500,"expenditureAmount":0}],"budgetExpenditureAmount":518500,"expenditureAmount":0,"budgetIncomeAmount":0,"incomeAmount":0,"__v":0},{"gps":null,"_id":"5c6ced2e42dd8914f1fdb683","profile":"5971ca164e7b8d5ea27f0488","year":2018,"etl":"5acdd6b5166dcc46cbcf4786","srcId":"514018","name":"ZŠ TGM horolezecká stěna","items":[],"paragraphs":[{"_id":"5c6ced2e42dd8914f1fdb8fa","id":"3113","budgetExpenditureAmount":500000,"expenditureAmount":0}],"budgetExpenditureAmount":500000,"expenditureAmount":0,"budgetIncomeAmount":0,"incomeAmount":0,"__v":0},{"gps":null,"_id":"5c6ced2e42dd8914f1fdb684","profile":"5971ca164e7b8d5ea27f0488","year":2018,"etl":"5acdd6b5166dcc46cbcf4786","srcId":"515018","name":"ZŠ TGM reko stávající nouzového osv","items":[],"paragraphs":[{"_id":"5c6ced2e42dd8914f1fdb8fc","id":"3113","budgetExpenditureAmount":250000,"expenditureAmount":0}],"budgetExpenditureAmount":250000,"expenditureAmount":0,"budgetIncomeAmount":0,"incomeAmount":0,"__v":0},{"gps":null,"_id":"5c6ced2e42dd8914f1fdb685","profile":"5971ca164e7b8d5ea27f0488","year":2018,"etl":"5acdd6b5166dcc46cbcf4786","srcId":"517018","name":"ZŠ Stross. n. - reko výměníkové stanice","items":[],"paragraphs":[{"_id":"5c6ced2e42dd8914f1fdb8fe","id":"3113","budgetExpenditureAmount":0,"expenditureAmount":0}],"budgetExpenditureAmount":0,"expenditureAmount":0,"budgetIncomeAmount":0,"incomeAmount":0,"__v":0},{"gps":null,"_id":"5c6ced2e42dd8914f1fdb686","profile":"5971ca164e7b8d5ea27f0488","year":2018,"etl":"5acdd6b5166dcc46cbcf4786","srcId":"520018","name":"MŠ U Průhonu - rekonstrukce","items":[],"paragraphs":[{"_id":"5c6ced2e42dd8914f1fdb900","id":"3111","budgetExpenditureAmount":282000,"expenditureAmount":0}],"budgetExpenditureAmount":282000,"expenditureAmount":0,"budgetIncomeAmount":0,"incomeAmount":0,"__v":0},{"gps":null,"_id":"5c6ced2e42dd8914f1fdb687","profile":"5971ca164e7b8d5ea27f0488","year":2018,"etl":"5acdd6b5166dcc46cbcf4786","srcId":"434016","name":"Rekonstrukce nebytového prostoru  Jankovcova 864","items":[],"paragraphs":[{"_id":"5c6ced2e42dd8914f1fdb902","id":"3613","budgetExpenditureAmount":20000,"expenditureAmount":0}],"budgetExpenditureAmount":20000,"expenditureAmount":0,"budgetIncomeAmount":0,"incomeAmount":0,"__v":0},{"gps":null,"_id":"5c6ced2e42dd8914f1fdb688","profile":"5971ca164e7b8d5ea27f0488","year":2018,"etl":"5acdd6b5166dcc46cbcf4786","srcId":"365014","name":"Reko vzduchotechn. a rozvodu tepla Bio Oko","items":[],"paragraphs":[{"_id":"5c6ced2e42dd8914f1fdb904","id":"3313","budgetExpenditureAmount":491700,"expenditureAmount":0}],"budgetExpenditureAmount":491700,"expenditureAmount":0,"budgetIncomeAmount":0,"incomeAmount":0,"__v":0},{"gps":null,"_id":"5c6ced2e42dd8914f1fdb689","profile":"5971ca164e7b8d5ea27f0488","year":2018,"etl":"5acdd6b5166dcc46cbcf4786","srcId":"451016","name":"Investiční rezerva OMA","items":[],"paragraphs":[{"_id":"5c6ced2e42dd8914f1fdb906","id":"3612","budgetExpenditureAmount":100000,"expenditureAmount":0}],"budgetExpenditureAmount":100000,"expenditureAmount":0,"budgetIncomeAmount":0,"incomeAmount":0,"__v":0},{"gps":null,"_id":"5c6ced2e42dd8914f1fdb68a","profile":"5971ca164e7b8d5ea27f0488","year":2018,"etl":"5acdd6b5166dcc46cbcf4786","srcId":"525018","name":"Reko výtahů (I.etapa - 3 domy)","items":[],"paragraphs":[{"_id":"5c6ced2e42dd8914f1fdb908","id":"3612","budgetExpenditureAmount":3000000,"expenditureAmount":0}],"budgetExpenditureAmount":3000000,"expenditureAmount":0,"budgetIncomeAmount":0,"incomeAmount":0,"__v":0},{"gps":null,"_id":"5c6ced2e42dd8914f1fdb68b","profile":"5971ca164e7b8d5ea27f0488","year":2018,"etl":"5acdd6b5166dcc46cbcf4786","srcId":"81018","name":"SFZ 2018","items":[],"paragraphs":[{"_id":"5c6ced2e42dd8914f1fdb90b","id":"6112","budgetExpenditureAmount":0,"expenditureAmount":0},{"_id":"5c6ced2e42dd8914f1fdb90a","id":"6171","budgetExpenditureAmount":0,"expenditureAmount":0}],"budgetExpenditureAmount":0,"expenditureAmount":0,"budgetIncomeAmount":0,"incomeAmount":0,"__v":0},{"gps":null,"_id":"5c6ced2e42dd8914f1fdb68c","profile":"5971ca164e7b8d5ea27f0488","year":2018,"etl":"5acdd6b5166dcc46cbcf4786","srcId":"2016","name":"Nadační fond","items":[],"paragraphs":[{"_id":"5c6ced2e42dd8914f1fdb90d","id":"4339","budgetExpenditureAmount":35700,"expenditureAmount":0}],"budgetExpenditureAmount":35700,"expenditureAmount":0,"budgetIncomeAmount":0,"incomeAmount":0,"__v":0},{"gps":null,"_id":"5c6ced2e42dd8914f1fdb68d","profile":"5971ca164e7b8d5ea27f0488","year":2018,"etl":"5acdd6b5166dcc46cbcf4786","srcId":"11","name":"Ekologický fond","items":[],"paragraphs":[{"_id":"5c6ced2e42dd8914f1fdb90f","id":"6409","budgetExpenditureAmount":60100,"expenditureAmount":0}],"budgetExpenditureAmount":60100,"expenditureAmount":0,"budgetIncomeAmount":0,"incomeAmount":0,"__v":0}]